joestudymodule/__init__.py
joestudymodule/add.py
joestudymodule/subtract.py
joestudymodule/extras/__init__.py
joestudymodule/extras/divide.py
joestudymodule/extras/multiply.py
verysimplemoduleboyuan-0.0.1.dist-info/METADATA
verysimplemoduleboyuan-0.0.1.dist-info/WHEEL
verysimplemoduleboyuan-0.0.1.dist-info/top_level.txt
verysimplemoduleboyuan-0.0.1.dist-info/RECORD
