Metadata-Version: 2.1
Name: verysimplemoduleboyuan
Version: 0.0.1
Summary: My first Python package
Author: Happy Learner
Author-email: 
Keywords: python,first package
Classifier: Development Status :: 3 - Alpha
Classifier: Intended Audience :: Education
Classifier: Programming Language :: Python :: 2
Classifier: Programming Language :: Python :: 3
Classifier: Operating System :: MacOS :: MacOS X
Classifier: Operating System :: Microsoft :: Windows
